aioneo4j/__init__.py
aioneo4j/client.py
aioneo4j/errors.py
aioneo4j/transport.py
aioneo4j/utils.py
aioneo4j-0.0.5.dist-info/DESCRIPTION.rst
aioneo4j-0.0.5.dist-info/METADATA
aioneo4j-0.0.5.dist-info/RECORD
aioneo4j-0.0.5.dist-info/WHEEL
aioneo4j-0.0.5.dist-info/metadata.json
aioneo4j-0.0.5.dist-info/top_level.txt
