Metadata-Version: 2.0
Name: aioneo4j
Version: 0.0.5
Summary: asyncio client for neo4j
Home-page: https://github.com/wikibusiness/aioneo4j
Author: wikibusiness
Author-email: osf@wikibusiness.org
License: UNKNOWN
Keywords: neo4j,asyncio,aiohttp
Platform: UNKNOWN
Classifier: Development Status :: 5 - Production/Stable
Classifier: Intended Audience :: Developers
Classifier: License :: OSI Approved :: MIT License
Classifier: Operating System :: POSIX
Classifier: Operating System :: MacOS :: MacOS X
Classifier: Operating System :: Microsoft :: Windows
Classifier: Programming Language :: Python
Classifier: Programming Language :: Python :: 3
Classifier: Programming Language :: Python :: 3.4
Classifier: Programming Language :: Python :: 3.5
Classifier: Programming Language :: Python :: 3.6
Requires-Dist: aiohttp (>=2.3.6)
Requires-Dist: async-timeout
